.gitignore
LICENSE
README.md
addrxlat.h
ffi_addrxlat.py
ffi_kdumpfile.py
kdumpfile.h
pyproject.toml
setup.cfg
setup.py
addrxlat/__init__.py
addrxlat/constants.py
addrxlat/defs_py2.py
addrxlat/defs_py3.py
addrxlat/exceptions.py
addrxlat/objects.py
addrxlat/utils.py
kdumpfile/__init__.py
kdumpfile/constants.py
kdumpfile/defs_py2.py
kdumpfile/defs_py3.py
kdumpfile/exceptions.py
kdumpfile/objects.py
kdumpfile/utils.py
pykdumpfile.egg-info/PKG-INFO
pykdumpfile.egg-info/SOURCES.txt
pykdumpfile.egg-info/dependency_links.txt
pykdumpfile.egg-info/requires.txt
pykdumpfile.egg-info/top_level.txt
tests/test_addrxlat.py
tests/test_kdumpfile.py